django_ogp/__init__.py
django_ogp/admin.py
django_ogp/apps.py
django_ogp/models.py
django_ogp/migrations/0001_initial.py
django_ogp/migrations/__init__.py
django_ogp/templates/django_app/ogp.html
django_ogp/templatetags/__init__.py
django_ogp/templatetags/ogp.py
django_ogp/tests/__init__.py
django_ogp/tests/settings.py
django_ogp/tests/test_ogp/__init__.py
django_ogp/tests/test_ogp/test_admin.py
django_ogp/tests/test_ogp/test_models.py
django_ogp/tests/test_ogp/test_ogp.py
django_ogp/tests/test_ogp/test_ogp_nodata.py
django_ogp-0.0b7.dist-info/LICENSE
django_ogp-0.0b7.dist-info/METADATA
django_ogp-0.0b7.dist-info/WHEEL
django_ogp-0.0b7.dist-info/top_level.txt
django_ogp-0.0b7.dist-info/RECORD
