Metadata-Version: 2.1
Name: django-ogp
Version: 0.0b7
Summary: A more dynamic way to register Open Graph protocol
Home-page: https://github.com/ricardochaves/django_ogp
Author: Ricardo Baltazar Chaves
Author-email: ricardobchaves6@gmail.com
License: MIT
Platform: UNKNOWN
Classifier: Programming Language :: Python
Classifier: Programming Language :: Python :: 3
Classifier: Programming Language :: Python :: 3.5
Classifier: Programming Language :: Python :: 3.7
Classifier: Framework :: Django :: 2.0
Classifier: Framework :: Django :: 2.1
Classifier: Environment :: Web Environment
Classifier: Natural Language :: Portuguese (Brazilian)
Classifier: Development Status :: 4 - Beta
Classifier: Framework :: Django
Classifier: Intended Audience :: Developers
Classifier: License :: OSI Approved :: MIT License
Classifier: Operating System :: OS Independent
